MANIFEST.in
README.md
__init__.py
example.py
linear_regression.py
setup.py
tqdm_example.py
tf_progress/__init__.py
tf_progress/tf_progress.py
tf_progress.egg-info/PKG-INFO
tf_progress.egg-info/SOURCES.txt
tf_progress.egg-info/dependency_links.txt
tf_progress.egg-info/entry_points.txt
tf_progress.egg-info/not-zip-safe
tf_progress.egg-info/top_level.txt