Metadata-Version: 1.0
Name: tf-progress
Version: 0.1.2
Summary: Easy-to-use library for logging training progress of TensorFlow
Home-page: https://github.com/tobegit3hub/tf_progress
Author: tobe
Author-email: tobeg3oogle@gmail.com
License: UNKNOWN
Platform: UNKNOWN
